anysqldiag/__init__.py
anysqldiag/__main__.py
anysqldiag/anysqldiag.py
anysqldiag/utils.py
anysqldiag-0.0.4.dist-info/LICENSE
anysqldiag-0.0.4.dist-info/METADATA
anysqldiag-0.0.4.dist-info/WHEEL
anysqldiag-0.0.4.dist-info/entry_points.txt
anysqldiag-0.0.4.dist-info/top_level.txt
anysqldiag-0.0.4.dist-info/RECORD
