Metadata-Version: 2.1
Name: anysqldiag
Version: 0.0.4
Summary: CLI to diagnose any SQL using sqlglot
Home-page: https://github.com/Minyus/any-sql-diag
Author: Yusuke Minami
Author-email: me@minyus.github.com
License: MIT
Keywords: SQL,sqlglot,Athena,BigQuery,ClickHouse,Databricks,Doris,Drill,Druid,DuckDB,Dune,Hive,Materialize,MySQL,Oracle,Postgres,Presto,PRQL,Redshift,RisingWave,Snowflake,Spark,Spark2,SQLite,StarRocks,Tableau,Teradata,Trino,TSQL
Classifier: Development Status :: 3 - Alpha
Classifier: Natural Language :: English
Classifier: Programming Language :: Python :: 3.8
Classifier: Programming Language :: Python :: 3.9
Classifier: Programming Language :: Python :: 3.10
Classifier: Programming Language :: Python :: 3.11
Classifier: Programming Language :: Python :: 3.12
Classifier: Programming Language :: Python :: 3.13
Classifier: Operating System :: OS Independent
License-File: LICENSE
Requires-Dist: fire
Requires-Dist: sqlglot[rs]
